{
  "accounts": {
    "1599879": {
      "account_id": "1599879",
      "accNum": "10",
      "starting_balance": 46632.85,
      "max_drawdown_balance": 45132.85,
      "tier_size": 50000,
      "tier_name": "50k",
      "drawdown_percentage": 3.0,
      "drawdown_limit": 1500.0,
      "last_reset": "2025-11-04T00:00:00.000000-04:00",
      "status": "ACTIVE"
    },
    "1605169": {
      "account_id": "1605169",
      "accNum": "11",
      "starting_balance": 50922.58,
      "max_drawdown_balance": 49422.58,
      "tier_size": 50000,
      "tier_name": "50k",
      "drawdown_percentage": 3.0,
      "drawdown_limit": 1500.0,
      "last_reset": "2025-11-04T00:00:00.000000-04:00",
      "status": "ACTIVE"
    }
  },
  "last_updated": "2025-11-04T00:00:00.000000-04:00"
}